StreamIndicator/__init__.py
StreamIndicator-1.0.3.dist-info/LICENSE
StreamIndicator-1.0.3.dist-info/LICENSE copy
StreamIndicator-1.0.3.dist-info/METADATA
StreamIndicator-1.0.3.dist-info/WHEEL
StreamIndicator-1.0.3.dist-info/top_level.txt
StreamIndicator-1.0.3.dist-info/RECORD
