Metadata-Version: 2.1
Name: StreamIndicator
Version: 1.0.3
Summary: Plotly Indicator Gauge Chart
Home-page: https://github.com/REPNOT/StreamIndicator
Author: Derek Evans
Author-email: derek.evans@deinfoservice.com
Requires-Python: >=3.7
License-File: LICENSE
License-File: LICENSE copy
Requires-Dist: streamlit >=0.63
Requires-Dist: plotly ==5.17.0
Provides-Extra: devel
Requires-Dist: wheel ; extra == 'devel'
Requires-Dist: pytest ==7.4.0 ; extra == 'devel'
Requires-Dist: playwright ==1.36.0 ; extra == 'devel'
Requires-Dist: requests ==2.31.0 ; extra == 'devel'
Requires-Dist: pytest-playwright-snapshot ==1.0 ; extra == 'devel'
Requires-Dist: pytest-rerunfailures ==12.0 ; extra == 'devel'
Requires-Dist: plotly ==5.17.0 ; extra == 'devel'
